{"Mem":[5954.7, 471.3, 1790.9, 3692.5],"Disk":[["/dev/sdb7","104859644","63409444","41450200","61%"],["/dev/sda2","62923224","43612172","16120868","74%"],["/dev/sda1","54296576","39544244","12571084","76%"]],"Time":"2018/10/03 08:34:17 -0600","Users":["demonelf"],"Uptime":["08:34:17up13:04","1user","0.30","0.33","0.31"],"CPU_Cores":2,"CPU_Name":" Intel(R) Core(TM)2 Duo CPU P8800 @ 2.66GHz","Network":[["enp12s0", "0.00", "0.00", "0.00", "0.00", "0.00", "0.00"],["ip6tnl0", "0.00", "0.00", "0.00", "0.00", "0.00", "0.00"],["sit0", "0.00", "0.00", "0.00", "0.00", "0.00", "0.00"]],"CPUs":[["all", 13.96, 0.02, 5.20, 1.69, 0.00, 0.24, 0.00, 0.00, 0.00, 78.89],["0", 10.38, 0.02, 3.81, 1.92, 0.00, 0.14, 0.00, 0.00, 0.00, 83.74],["1", 21.47, 0.04, 8.12, 1.22, 0.00, 0.44, 0.00, 0.00, 0.00, 68.72]],"Process_10T_CPU":[["4302", "4.6", "demonelf","chrome"],["7422", "4.4", "demonelf","gnome-shell"],["3886", "1.8", "root","X"],["18903", "1.5", "demonelf","mplayer"],["4863", "1.0", "demonelf","chrome"],["18217", "1.0", "demonelf","chrome"],["18286", "1.0", "demonelf","gvim"],["16084", "0.7", "demonelf","chrome"],["18059", "0.5", "root","kworker/0:2"],["3974", "0.3", "demonelf","pulseaudio"]],"Process_10T_Mem":[["4302", "6.2", "demonelf","chrome"],["7422", "4.4", "demonelf","gnome-shell"],["4863", "3.1", "demonelf","chrome"],["16084", "2.4", "demonelf","chrome"],["4590", "2.3", "demonelf","chrome"],["7584", "2.2", "demonelf","gvim"],["3622", "1.9", "gdm","gnome-shell"],["17519", "1.9", "demonelf","chrome"],["18217", "1.9", "demonelf","chrome"],["9255", "1.8", "demonelf","chrome"]],"LastError":["[ 3617.308418] traps: gnome-shell[3965] trap int3 ip:7fdf99b472f1 sp:7ffee5e8cfa0 error:0 in libglib-2.0.so.0.5200.3[7fdf99af7000+111000]", "[ 21.694909] gsd-xsettings[4093]: segfault at 1 ip 00007f8512482a93 sp 00007ffc6ace0380 error 4 in libgobject-2.0.so.0.5200.3[7f851244d000+53000]", "[ 1.575816] platform regulatory.0: Direct firmware load for regulatory.db failed with error -2"],"LastWar":["[ 2.704014] systemd[1]: Proceeding WITHOUT firewalling in effect! (This warning is only shown for the first loaded unit using IP firewalling.)", "[ 0.170002] ACPI BIOS Warning (bug): Incorrect checksum in table [SSDT] - 0x37, should be 0xC7 (20170831/tbprint-211)", "[ 0.168357] ACPI BIOS Warning (bug): Incorrect checksum in table [SSDT] - 0xA0, should be 0x2F (20170831/tbprint-211)", "[ 0.000000] ACPI BIOS Warning (bug): Incorrect checksum in table [ATKG] - 0xEA, should be 0x53 (20170831/tbprint-211)", "[ 0.000000] ACPI BIOS Warning (bug): 32/64X length mismatch in FADT/Gpe0Block: 128/64 (20170831/tbfadt-603)"],"Files":[],"Install_System_Type":0,"Update":[]}
